rlock/__init__.py
rlock/api.py
rlock/file.py
rlock/sql.py
rlock-0.0.5.dist-info/LICENSE
rlock-0.0.5.dist-info/METADATA
rlock-0.0.5.dist-info/WHEEL
rlock-0.0.5.dist-info/top_level.txt
rlock-0.0.5.dist-info/RECORD
