Metadata-Version: 2.1
Name: rlock
Version: 0.0.5
Summary: A RedLock API Client
Home-page: https://github.com/cloudcraeft/rlock
Author: cloudcraeft
Author-email: cloudcraeft@outlook.com
License: MIT License
Requires-Dist: requests
